the_ark/__init__.py
the_ark/actions.py
the_ark/email_client.py
the_ark/field_handlers.py
the_ark/input_generator.py
the_ark/picard_client.py
the_ark/rhino_client.py
the_ark/s3_client.py
the_ark/screen_capture.py
the_ark/selenium_helpers.py
the_ark/resources/__init__.py
the_ark/resources/action_constants.py
the_ark/resources/action_schema.py
the_ark/resources/schema_validator.py
theark-0.0.9.dist-info/DESCRIPTION.rst
theark-0.0.9.dist-info/METADATA
theark-0.0.9.dist-info/RECORD
theark-0.0.9.dist-info/WHEEL
theark-0.0.9.dist-info/metadata.json
theark-0.0.9.dist-info/top_level.txt
