Metadata-Version: 2.0
Name: theark
Version: 0.0.9
Summary: meltQA Tools Common Library.
Home-page: https://github.com/meltmedia/the-ark
Author: meltmedia QA Team
Author-email: qa-d@meltmedia.com
License: Apache Software License
Keywords: selenium helpers qa automation
Platform: UNKNOWN
Classifier: Development Status :: 1 - Planning
Classifier: Topic :: Utilities
Classifier: Programming Language :: Python :: 2.7
Classifier: License :: OSI Approved :: Apache Software License
Requires-Dist: boto (>=2.29.1)
Requires-Dist: requests (>=2.3.0)
Requires-Dist: selenium (>=2.53.0)
